{
    "nixpkgs": {
        "branch": "nixos-unstable",
        "description": "Nixpkgs/NixOS branches that track the Nixpkgs/NixOS channels",
        "homepage": "https://github.com/NixOS/nixpkgs",
        "owner": "NixOS",
        "repo": "nixpkgs-channels",
        "rev": "d363be93b4957fce418a00340edc8b9bad5a1c88",
        "sha256": "1fxrd3h799iv7jbrwcj9yspqfgmhjngwxmdrn2laxa97h4g9g7qf",
        "type": "tarball",
        "url": "https://github.com/NixOS/nixpkgs-channels/archive/d363be93b4957fce418a00340edc8b9bad5a1c88.tar.gz",
        "url_template": "https://github.com/<owner>/<repo>/archive/<rev>.tar.gz"
    }
}
